{"index": 0, "name": "better than takeout sweet thai basil chicken", "ingredients": {"ground chicken": "1 pound", "seasame oil": "2 tablespoons", "black pepper": "to taste", "garlic": "4 cloves", "ginger": "1 inch, grated", "bell pepper, red or orange": "2, chopped", "cashews": "1/2 cup", "soy sauce, low sodium": "1/2 cup", "fish sauce": "2 tablespoons", "honey": "1/4 cup", "chili paste, sambal oelek": "2-3 tablespoons", "basil": "1 cup, torn", "mint": "1/4 cup, torn", "rice, white or brown": "as needed", "mango": "1, sliced or diced"}, "instructions": {"1": "Heat the oil in a large skillet over medium heat. When the oil shimmers, add the chicken. Season with black pepper and brown all over, breaking the chicken up as it cooks, about 5 minutes. Add the garlic, ginger, peppers, and cashews, cook another 2-3 minutes, until the garlic is fragrant. Pour in the soy sauce, fish sauce, chili paste, and honey. Bring the sauce to a boil over medium-high heat and cook until the sauce coats the chicken, about 5-8 minutes.", "2": "Remove from the heat and stir in the basil and mint.", "3": "Serve the chicken and sauce over bowls of rice. Top with mangos and additional basil. Enjoy!"}, "cuisine": ["thai", "asian"], "tags": ["easy leftovers", "one pot meal", "spicy"]}
